nomad/__init__.py
nomad/client.py
nomad/models/__init__.py
nomad/models/allocation.py
nomad/models/constraint.py
nomad/models/deployment.py
nomad/models/evaluation.py
nomad/models/event_stream.py
nomad/models/job.py
nomad/models/node.py
nomad/models/resource.py
nomad/models/service.py
nomad/models/task.py
nomad/py.typed
nomad_api-0.0.2.dist-info/LICENSE
nomad_api-0.0.2.dist-info/WHEEL
nomad_api-0.0.2.dist-info/METADATA
nomad_api-0.0.2.dist-info/RECORD
